{
  "heroes": [
    {"name": "Abaddon", "file": "hero_data/abaddon.json"},
    {"name": "Alchemist", "file": "hero_data/alchemist.json"},
    {"name": "Ancient Apparition", "file": "hero_data/аncient_аpparition.json"},
    {"name": "Anti-Mage", "file": "hero_data/anti_mage.json"},
    {"name": "Arc Warden", "file": "hero_data/arc_warden.json"},
    {"name": "Axe", "file": "hero_data/axe.json"},
    {"name": "Bane", "file": "hero_data/bane.json"},
    {"name": "Batrider", "file": "hero_data/batrider.json"},
    {"name": "Beastmaster", "file": "hero_data/beastmaster.json"},
    {"name": "Bloodseeker", "file": "hero_data/bloodseeker.json"},
    {"name": "Bounty Hunter", "file": "hero_data/bounty_hunter.json"},
    {"name": "Brewmaster", "file": "hero_data/brewmaster.json"},
    {"name": "Bristleback", "file": "hero_data/bristleback.json"},
    {"name": "Broodmother", "file": "hero_data/broodmother.json"},
    {"name": "Centaur Warrunner", "file": "hero_data/centaur_warrunner.json"},
    {"name": "Chaos Knight", "file": "hero_data/chaos_knight.json"},
    {"name": "Chen", "file": "hero_data/chen.json"},
    {"name": "Clinkz", "file": "hero_data/clinkz.json"},
    {"name": "Clockwerk", "file": "hero_data/clockwerk.json"},
    {"name": "Crystal Maiden", "file": "hero_data/crystal_maiden.json"},
    {"name": "Dark Seer", "file": "hero_data/dark_seer.json"},
    {"name": "Dark Willow", "file": "hero_data/dark_willow.json"},
    {"name": "Dawnbreaker", "file": "hero_data/dawnbreaker.json"},
    {"name": "Dazzle", "file": "hero_data/dazzle.json"},
    {"name": "Death Prophet", "file": "hero_data/death_prophet.json"},
    {"name": "Disruptor", "file": "hero_data/disruptor.json"},
    {"name": "Doom", "file": "hero_data/doom.json"},
    {"name": "Dragon Knight", "file": "hero_data/dragon_knight.json"},
    {"name": "Drow Ranger", "file": "hero_data/drow_ranger.json"},
    {"name": "Earth Spirit", "file": "hero_data/earth_spirit.json"},
    {"name": "Earthshaker", "file": "hero_data/earthshaker.json"},
    {"name": "Elder Titan", "file": "hero_data/elder_titan.json"},
    {"name": "Ember Spirit", "file": "hero_data/ember_spirit.json"},
    {"name": "Enchantress", "file": "hero_data/enchantress.json"},
    {"name": "Enigma", "file": "hero_data/enigma.json"},
    {"name": "Faceless Void", "file": "hero_data/faceless_void.json"},
    {"name": "Grimstroke", "file": "hero_data/grimstroke.json"},
    {"name": "Gyrocopter", "file": "hero_data/gyrocopter.json"},
    {"name": "Hoodwink", "file": "hero_data/hoodwink.json"},
    {"name": "Huskar", "file": "hero_data/huskar.json"},
    {"name": "Juggernaut", "file": "hero_data/juggernaut.json"},
    {"name": "Keeper of the Light", "file": "hero_data/keeper_of_the_light.json"},
    {"name": "Kunkka", "file": "hero_data/kunkka.json"},
    {"name": "Legion Commander", "file": "hero_data/legion_commander.json"},
    {"name": "Leshrac", "file": "hero_data/leshrac.json"},
    {"name": "Lich", "file": "hero_data/lich.json"},
    {"name": "Lifestealer", "file": "hero_data/lifestealer.json"},
    {"name": "Lina", "file": "hero_data/lina.json"},
    {"name": "Lion", "file": "hero_data/lion.json"},
    {"name": "Lone Druid", "file": "hero_data/lone_druid.json"},
    {"name": "Luna", "file": "hero_data/luna.json"},
    {"name": "Lycan", "file": "hero_data/lycan.json"},
    {"name": "Magnus", "file": "hero_data/magnus.json"},
    {"name": "Marci", "file": "hero_data/marci.json"},
    {"name": "Mars", "file": "hero_data/mars.json"},
    {"name": "Medusa", "file": "hero_data/medusa.json"},
    {"name": "Meepo", "file": "hero_data/meepo.json"},
    {"name": "Mirana", "file": "hero_data/mirana.json"},
    {"name": "Monkey King", "file": "hero_data/monkey_king.json"},
    {"name": "Morphling", "file": "hero_data/morphling.json"},
    {"name": "Muerta", "file": "hero_data/muerta.json"},
    {"name": "Naga Siren", "file": "hero_data/naga_siren.json"},
    {"name": "Natures Prophet", "file": "hero_data/natures_prophet.json"},
    {"name": "Necrophos", "file": "hero_data/necrophos.json"},
    {"name": "Night Stalker", "file": "hero_data/night_stalker.json"},
    {"name": "Nyx Assassin", "file": "hero_data/nyx_assassin.json"},
    {"name": "Ogre Magi", "file": "hero_data/ogre_magi.json"},
    {"name": "Omniknight", "file": "hero_data/omniknight.json"},
    {"name": "Oracle", "file": "hero_data/oracle.json"},
    {"name": "Outworld Destroyer", "file": "hero_data/outworld_destroyer.json"},
    {"name": "Pangolier", "file": "hero_data/pangolier.json"},
    {"name": "Phantom Assassin", "file": "hero_data/phantom_assassin.json"},
    {"name": "Phantom Lancer", "file": "hero_data/phantom_lancer.json"},
    {"name": "Phoenix", "file": "hero_data/phoenix.json"},
    {"name": "Primal Beast", "file": "hero_data/primal_beast.json"},
    {"name": "Puck", "file": "hero_data/puck.json"},
    {"name": "Pudge", "file": "hero_data/pudge.json"},
    {"name": "Pugna", "file": "hero_data/pugna.json"},
    {"name": "Queen of Pain", "file": "hero_data/queen_of_pain.json"},
    {"name": "Razor", "file": "hero_data/razor.json"},
    {"name": "Riki", "file": "hero_data/riki.json"},
    {"name": "Rubick", "file": "hero_data/rubick.json"},
    {"name": "Sand King", "file": "hero_data/sand_king.json"},
    {"name": "Shadow Demon", "file": "hero_data/shadow_demon.json"},
    {"name": "Shadow Fiend", "file": "hero_data/shadow_fiend.json"},
    {"name": "Shadow Shaman", "file": "hero_data/shadow_shaman.json"},
    {"name": "Silencer", "file": "hero_data/silencer.json"},
    {"name": "Skywrath Mage", "file": "hero_data/skywrath_mage.json"},
    {"name": "Slardar", "file": "hero_data/slardar.json"},
    {"name": "Slark", "file": "hero_data/slark.json"},
    {"name": "Snapfire", "file": "hero_data/snapfire.json"},
    {"name": "Sniper", "file": "hero_data/sniper.json"},
    {"name": "Spectre", "file": "hero_data/spectre.json"},
    {"name": "Spirit Breaker", "file": "hero_data/spirit_breaker.json"},
    {"name": "Storm Spirit", "file": "hero_data/storm_spirit.json"},
    {"name": "Sven", "file": "hero_data/sven.json"},
    {"name": "Techies", "file": "hero_data/techies.json"},
    {"name": "Templar Assassin", "file": "hero_data/templar_assassin.json"},
    {"name": "Terrorblade", "file": "hero_data/terrorblade.json"},
    {"name": "Tidehunter", "file": "hero_data/tidehunter.json"},
    {"name": "Timbersaw", "file": "hero_data/timbersaw.json"},
    {"name": "Tinker", "file": "hero_data/tinker.json"},
    {"name": "Tiny", "file": "hero_data/tiny.json"},
    {"name": "Treant Protector", "file": "hero_data/treant_protector.json"},
    {"name": "Troll Warlord", "file": "hero_data/troll_warlord.json"},
    {"name": "Tusk", "file": "hero_data/tusk.json"},
    {"name": "Underlord", "file": "hero_data/underlord.json"},
    {"name": "Undying", "file": "hero_data/undying.json"},
    {"name": "Ursa", "file": "hero_data/ursa.json"},
    {"name": "Vengeful Spirit", "file": "hero_data/vengeful_spirit.json"},
    {"name": "Venomancer", "file": "hero_data/venomancer.json"},
    {"name": "Viper", "file": "hero_data/viper.json"},
    {"name": "Visage", "file": "hero_data/visage.json"},
    {"name": "Void Spirit", "file": "hero_data/void_spirit.json"},
    {"name": "Warlock", "file": "hero_data/warlock.json"},
    {"name": "Weaver", "file": "hero_data/weaver.json"},
    {"name": "Windranger", "file": "hero_data/windranger.json"},
    {"name": "Winter Wyvern", "file": "hero_data/winter_wyvern.json"},
    {"name": "Witch Doctor", "file": "hero_data/witch_doctor.json"},
    {"name": "Wraith King", "file": "hero_data/wraith_king.json"},
    {"name": "Zeus", "file": "hero_data/zeus.json"}
  ]
}
